{
  "slug": "isadepaeva-kingitus",
  "category": "gifts",
  "title": "Isadepäeva kingitus 2026: mõistlik plaan ja tugev emotsioon",
  "description": "Isadepäeva kingitus 2026 Eestis: portree fotost, eelvaade, tarne üle Eesti ja varajane tellimus enne isadepäeva tipuhooaega.",
  "publishedAt": "2026-10-20",
  "author": {
    "name": "PopArt.ee",
    "url": "https://www.popart.ee",
    "jobTitle": "Kunstiteenus"
  },
  "coverImage": "/og-image.jpg",
  "keywords": [
    "isadepäeva kingitus",
    "isadepäeva kingitus 2026",
    "kingitus isale",
    "Tallinn"
  ],
  "bodyHtml": "<p>Isadepäeva kingitus ei pea olema järjekordne vidin. Portree annab isale mälestuse, mis on kodus näha — aga tellimuse edu sõltub ikka samadest asjadest: hea foto, eelvaade ja tarne üle Eesti, mis on planeeritud nii, et te ei peaks jõudma kulleriga võistelma.</p>\n<h2>Isadepäeva kingitus: miks varajane tellimus on hooaja võit</h2>\n<p>isadepäeva kingitus kontekstis on kõige kallim viga see, kui tähtaeg “libiseb” viimasele nädalale. Hooajal võib järjekord pikeneda ja eelvaatele jääb vähem ruumi.</p>\n<p>Kui te tellite Eestis ja tahate tarne üle Eesti, on aadressi täpsus sama oluline kui foto kvaliteet.</p>\n<p>Tallinn võib olla kiire suhtluspunkt, aga tellimuse kvaliteet sõltub ikka töötlusest, eelvaatest ja trükist.</p>\n<h2>Tarne üle Eesti ja tähtpäeva kingid</h2>\n<p>Tarne üle Eesti tähendab, et kingitus ei sõltu sellest, kas te elate Tallinnas, Tartus või väiksemas asulas — oluline on, et aadress oleks täpne ja kättesaamine oleks realistlik.</p>\n<p>Tallinn jääb paljudele mugavaks logistiliseks sõlmeks, sest kullerite sagedus ja kättesaamise aknad võivad olla painlikumad, aga lõpptulemus sõltub ikka tellimuse selgusest ja teie vastuse kiirusest eelvaatele.</p>\n<p>Kui te tahate jõuludeks kindlat päeva, ärge jätke tarne “õnnele”: kirjutage tellimuses kuupäev ja linn ning küsige vajadusel kinnitust, et graafik on realistlik.</p>\n<h2>Eelvaade enne trükki</h2>\n<p>Eelvaade enne trükki on kingi ostja parim kindlustus: te näete kompositsiooni, tausta sobivust ja seda, kas foto kannab valitud mõõtu.</p>\n<p>Kui eelvaade puudub, suureneb risk, et kingi emotsioon asendub pettumusega — eriti hooajal, kui te ei saa uut tellimust enam sisse mahutada.</p>\n<p>Premium positsioneerimine tähendab ka seda, et protsess ei sunni teid “õnnelikult arvama”: te kinnitate tulemuse enne lõplikku trükki.</p>\n<h2>Piiratud töömahud ja järjekord</h2>\n<p>Hooajal võib järjekord pikeneda: see ei ole dramatism, see on matemaatika — piiratud tööpäevad, rohkem tellimusi, sama trüki- ja pakendusressurss.</p>\n<p>Kui te kuulete sõnumit “planeerige varakult”, mõelge selle all päriselt: eelvaate kinnitus, trükk, pakendamine ja kullerivaheline päev.</p>\n<p>Varajane ost ei ole ainult “hea nõuanne” — see on kingi kvaliteedi osa, sest see annab ruumi parandustele ilma paanikata.</p>\n<h2>Kingipsühholoogia ja premium tunne</h2>\n<p>Kingi psühholoogia töötab siis, kui king tundub personaalselt valitud, aga mitte sunnitud: portree seab esile mälestuse ja annab kodule uue keskpunkti.</p>\n<p>Inimesed mäletavad kingi mitte hinna järgi, vaid emotsiooni järgi: “ta tõesti mõtles minust” on tugevam kui “ta kulutas palju”.</p>\n<p>Kui te kahtlete, kas king on piisavalt “suur”, mõelge hoopis, kas see on piisavalt “õige” — õige foto ja õige mõõt teevad kingi suuremaks kui liigne formaat.</p>\n<h2>Ostujuht: kontroll-loend enne tellimust</h2>\n<p>Foto on terav ja emotsioon on loomulik.</p>\n<p>Mõõt on mõistlik või teadlikult universaalne.</p>\n<p>Eelvaade on plaanis enne trükki.</p>\n<p>Tähtaeg on kirjas tellimuses.</p>\n<p>Tarne üle Eesti on kontrollitud aadressiga.</p>\n<h2>Kuidas valida foto, mis kõnetab kingisaajat</h2>\n<p>Valige hetk, mis ei vaja pikka selgitust: naer, kallistus, ühine päev või vaikne õnn.</p>\n<p>Kui te kahtlete kahe foto vahel, valige teravam — trükk näitab vigu.</p>\n<h2>Interjöör ja mõõt: vältige “vale koha” tunnet</h2>\n<p>Kui te ei tea seina mõõtu, tehke mockup või valige universaalsem formaat.</p>\n<p>Lisajuhendina vaadake <a href='/et/blog/seinapilt-tellimine'>seinapilt tellimine</a> artiklit.</p>\n<h2>Kuidas kirjutada kingikaardile lühike sõnum</h2>\n<p>Kolm lauset piisab: õnnitlus, miks see foto, miks see kingitus neile sobib.</p>\n<p>Portree teeb visuaalse töö ära — tekst toetab, mitte ei konkureeri.</p>\n<h2>Premium viimistlus: mida kingisaaja märgatakse</h2>\n<p>Teravus, värvitasakaal ja pakend — need detailid annavad tunde, et kingitus on “valmis”, mitte kiiruga kokku klopsitud.</p>\n<h2>Eesti tellija ja usaldus: miks “aus tähtaeg” müüb paremini kui kiirustamine</h2>\n<p>Kui te märkite tellimuses tähtaja kuupäevana ja linna, vähendate arusaamatust. See on eriti oluline hooajal, kui järjekord võib pikeneda.</p>\n<p>Tallinn võib tunduda kiire, aga tellimuste maht võib detsembris, mais või veebruaris teha graafiku vähem painlikuks kui tavaliselt.</p>\n<p>Kui te küsite enne makset ausalt, mis on jõutav, saate realistliku plaani — see on premium kogemuse osa.</p>\n<h2>Kuidas vältida “õige foto” üleanalüüsi, mis lükkab tellimuse liiga hiliseks</h2>\n<p>Määrake endale 20 minutit: kaks kandidaati, võrdlus teravuse ja emotsiooni järgi, otsus. Üleanalüüs on jõukatsumine järjekorraga.</p>\n<p>Kui te kahtlete, küsige sõbralt, kes tunneb kingisaajat — see ei vähenda kingi väärtust, see vähendab riski.</p>\n<p>Kui foto on tehniliselt nõrgem, aga emotsionaalselt õige, küsige enne makset ausat hinnangut trükis — parem aus vastus kui pettumus.</p>\n<h2>Tarne üle Eesti ja kingi kättesaamine: pakiautomaat vs ukseni</h2>\n<p>Pakiautomaat võib olla hea, kui pakk on tugev ja pilt on kaitstud. Ukseni tarne võib olla parem, kui te tahate vähendada paindumise riski.</p>\n<p>Kirjutage aadress täielikult: indeks, uksekood, korrus, kontaktnumber. Kuller ei pea arvama.</p>\n<p>Kui te ei saa vastu võtta, valige turvaline koht ja informeerige kingisaajat ette.</p>\n<h2>Kunstiline portree fotost kui kingi narratiiv (ilma pealetükkiva müügita)</h2>\n<p>Kingitusena portree seab esile mälestuse ja annab koju uue keskpunkti. See on tugev, kui te tahate, et king oleks nii isiklik kui ka püsiv.</p>\n<p>Kui te tahate süvendada stiili ja mõõtu enne otsust, lugege <a href='/et/blog/kunstiline-portree'>kunstiline portree</a> juhendit.</p>\n<p>Kui te mõtlete lõuendile, vaadake <a href='/et/blog/pilt-louendil'>pilt lõuendil</a> artiklit — see aitab mõista, mida lõuend kingisaajale tähendab.</p>\n<h2>Kingi “reaalsed tähtajad”: miks eelvaade + trükk + tarne ei mahu ühte päeva</h2>\n<p>Eelvaade nõuab teie tähelepanu; trükk nõuab tööd; pakendamine nõuab hoolt; tarne nõuab logistikat. Kui üks lüli venib, nihkub kogu graafik.</p>\n<p>Hooajal on see eriti aus: järjekord võib pikeneda ka siis, kui teie foto on ideaalne.</p>\n<p>Kui te jätate puhvri, on teil ruumi parandustele ilma paanikata — see on premium ostja taktika.</p>\n<h2>Tallinn vs maakond: mida see tähendab tellija jaoks praktikas</h2>\n<p>Tallinnas võib kättesaamise aknaid olla rohkem, aga tellimuste maht võib samuti olla suurem — need kaks tasakaalustavad üksteist.</p>\n<p>Maapiirkonnas võib kättesaamine olla vähem painlik, aga see ei ole probleem, kui te kirjutate aadressi täpselt ja jätate puhvri.</p>\n<p>Mõlemal juhul on võitja selge tellimus: tähtaeg, linn, kontakt, turvaline kättesaamise koht.</p>\n<h2>Kuidas kirjutada tellimuse märkused nii, et töö ei jääks “õnne” ootele</h2>\n<p>Hea märkus on konkreetne: tähtaeg kuupäevana, tarneaadress täielikult, eelistused ühes lauses (nt “rahulik taust”).</p>\n<p>Halb märkus on üldine palve ilma raamita — see sunnib tagasiotsuseid ja võtab aega.</p>\n<p>Kui teil on mitu tellimust, tehke nimed selgeks — hooajal segunevad tellimused kergesti.</p>\n<h2>Isadepäeva kingitus Eestis: märgi kuupäev kalendrisse</h2>\n<p>Isadepäeva kingitus tasub planeerida nagu projekt: foto, mõõt, eelvaade, trükk, tarne.</p>\n<p>Kui te tahate premium-tulemust, ärge jätke tellimust viimasele nädalale.</p>\n<h2>Isadepäev ja “vähem sõnu, rohkem tegu” kingid</h2>\n<p>Portree sobib hästi, sest see on tegu, mis jääb näha — ilma pikkade selgitusteta.</p>\n<h2>Isadepäeva kingitus: “vähem sõnu, rohkem tegu” võib tähendada ka portreed</h2><p>Isadepäeva kingitus ei pea olema järjekordne vidin. Portree on tegu, mis jääb koju nähtavale kohale — ilma pikkade selgitusteta.</p><p>Kui isa on reserveeritud, töötab sageli paremini rahulik stiil ja selge kompositsioon kui ülepaisutatud efektid.</p><p>Tallinn ja teised linnad pole siin erinevad põhimõttelt: edu võti on foto kvaliteet ja eelvaatega kinnitatud tulemus.</p><h2>Foto valik isale: lapsed, töö või ühine hobi — kuidas mitte eksida</h2><p>Kui te tahate rõhutada isa rolli, valige foto, kus suhe on näha: ühine mäng, õpetamine, naer või lihtsalt koos olemine.</p><p>Kui te tahate austust ilma sentimentaalsuseta, valige tugev portreehetk, kus emotsioon on kontrollitud.</p><p>Kui te kahtlete, küsige teiselt pereliikmelt — see ei vähenda kingi väärtust, see vähendab riski.</p><h2>Isadepäev ja tarne üle Eesti: kui te ei saa ise üle anda</h2><p>Tellides otse õigesse aadressi, vähendate vahepealseid samme. Kui see pole võimalik, valige turvaline kättesaamise koht ja tugev pakk.</p><p>Kirjutage tellimuses tähtaeg ja kontakt, et kuller ei peaks “arutlema”, kuhu pakk jätta.</p><p>Kui te planeerite ette, ei pea te isadepäeva hommikul kulleriga pinget tegema.</p><h2>Ettevõtte kontekst: kas portree on sobiv kingitus isale töö juures?</h2><p>See sõltub kultuurist ja fotost. Professionaalne ühisfoto või meeskonna mälestus võib olla turvalisem kui väga isiklik kaader.</p><p>Kui te ei tea, valige konservatiivsem kompositsioon ja rahulik taust — eelvaade annab teile kontrolli.</p><p>Kui king on eraisikule, saate olla vabam — aga ikka mõelge sellele, kuhu pilt koju läheb.</p><h2>Isadepäeva kingitus 2026 ja varajane ost: miks see on “mõistlik plaan”</h2><p>Isadepäeva kingitus tasub tellida nagu väike projekt: foto kogumine, mõõt, eelvaade, trükk, tarne. Kui üks lüli venib, venib kogu ahel.</p><p>Kui te loete seda artiklit varakult, olete juba võitnud: teil on aega parandusteks ilma paanikata.</p><p>Kui te loete hilja, märkige tellimuses tähtaeg ja küsige ausalt, mis on veel jõutav.</p><h2>Isadepäeva kingitus ja “vähe sõnu” kultuur: kuidas portree ütleb rohkem kui pikk kõne</h2><p>Paljud isad ei taha kingi juures suurt show’d. Portree töötab siin hästi, sest ta on vaikne kingitus, mis on samas tugev: ta on nähtav ja püsiv.</p><p>Kui te tahate lisada sõna, hoidke see konkreetne: miks see foto, mis see hetk tähendas teile.</p><p>Kui te kahtlete toonis, valige rahulik taust ja klassikaline kompositsioon — eelvaade kinnitab lõpptulemuse.</p><h2>Isale kingitus ja mõõt: kuidas mitte tellida “ülearu muljet”</h2><p>Suur pilt ei tähenda automaatselt suurt emotsiooni. Kui ruum on kompaktne või sein on juba täis, võib liiga suur mõõt tekitada koormuse.</p><p>Mockup aitab; kui te ei tea seina, valige universaalsem mõõt.</p><p>Lisaks vaadake <a href='/et/blog/pilt-louendil'>pilt lõuendil</a> juhendit, kui te kaalute lõuendit.</p><h2>Isadepäev ja lapsed: foto, mis räägib rollist ilma sõnadeleta</h2><p>Ühine mäng, õpetamine või lihtsalt koos naermine — need kaadrid töötavad sageli paremini kui sundposeeritud “õnnelik perekond”.</p><p>Kui lapsed on väikesed, kontrollige teravust: liikumine teeb fotod kiiresti pehmeks.</p><p>Kui te tahate rõhutada isa iseseisvat rolli, valige kaader, kus suhe on näha, aga stiil jääb rahulikuks.</p><h2>Isadepäeva kingitus Eestis ja tarne üle Eesti: millal on mõistlik tellida otse isale</h2><p>Kui te tahate üllatust, peab kättesaamine olema kindel: telefon, uksekood, turvaline koht. Üllatus ei tohi tähendada kaotatud pakki.</p><p>Kui te toote ise üle, planeerige rahulik aken — kiirustades üleandmine vähendab emotsiooni.</p><p>Tallinnas on logistika tihe, aga Eesti on väike — õige aadress lahendab palju.</p><h2>Isadepäeva kingitus 2026 ja varajane ost: miks see on talle ka signaal</h2><p>Varajane ost näitab, et te ei jätnud kingi juhuslikule nädalavahetusele. See on küpsusmärk — eriti täiskasvanud lastelt.</p><p>Kui te tellite varakult, on teil rohkem aega eelvaateks ja parandusteks.</p><p>Kui te olete valmis, alustage <a href='https://www.popart.ee'>PopArt.ee</a> tellimusest ja märkige tähtaeg selgelt.</p><h2>Kui isa on tehniline inimene: kuidas rääkida eelvaatest ilma “kontrollifriigiks” jäämata</h2><p>Eelvaade ei ole kahtlemine — see on kvaliteedikontroll. Kui te seda nii sõnastate, on paljudel meestel kergem sellega nõustuda.</p><p>Kui te tahate, et ta tunneks end kaasatud, küsige tema arvamust kahe tausta vahel — aga hoidke valikud piiratud, et otsustus ei veniks.</p><p>Kui te ei tea, kas ta tahab seina peale portreed, küsige vaikselt teiselt pereliikmelt — see säästab teid ebamugavast olukorrast.</p><h2>Isadepäeva kingitus: viimane kontroll-loend enne tellimust</h2><p>Kontrollige: foto teravus, mõõt (või universaalne valik), tähtaeg tellimuses, tarneaadress, eelvaate plaan.</p><p>Kui te loete seda hilja, märkige tähtaeg ja küsige ausalt, mis on veel jõutav — see säästab nii teid kui ka teenust ebarealistlikest ootustest.</p><p>Kui te olete valmis, alustage <a href='https://www.popart.ee'>PopArt.ee</a> tellimusest; varajane ost on isale sageli parim sõnum ilma pikkade sõnadeta.</p><h2>Isadepäeva kingitus ja kingi üleandmine: kuidas hoida emotsiooni ilma “suure show’ta”</h2><p>Paljud isad ei taha kingi juures tähelepanu tsentrit. Andke üle rahulikult, lühidalt ja konkreetselt: miks see foto.</p><p>Kui te ei saa ise kohale minna, tehke pakk tugevaks ja kirjutage selge juhis — isadepäeva hommikud on sageli kiired.</p><p>Kui te olete valmis, alustage <a href='https://www.popart.ee'>PopArt.ee</a> tellimusest ja märkige tähtaeg.</p><h2>Isadepäeva kingitus 2026: mõõt, sein ja “isa töötuba”</h2><p>Kui pilt läheb töötuppa, valige rahulik taust ja selge kompositsioon — liiga kodune dramaturgia võib tunduda ebakõlana.</p><p>Kui pilt läheb koju, saate olla soojem — aga ikkagi mõelge ruumi mõõtudele.</p><p>Mockup või universaalsem mõõt on parem kui liiga suur pilt, mis ei mahu kuhugi.</p><p>Lisaks vaadake <a href='/et/blog/seinapilt-tellimine'>seinapilt tellimine</a> artiklit, kui te kaalute suuremat formaati.</p><h2>Isadepäeva kingitus Eestis: varajane ost kui kingi kvaliteedi osa</h2><p>Varajane ost annab teenusele aega teha töö korrektselt ja teile aega kinnitada eelvaade rahulikult.</p><p>Kui te loete seda hilja, märkige tellimuses tähtaeg ja küsige ausalt, mis on veel jõutav.</p><p>Tallinn ja ülejäänud Eesti on mõlemad head, kui tellimus on kirjutatud selgelt.</p><p>Kui te kingite korraga mitmele isale (nt isa ja vanaisa), tehke iga tellimuse jaoks eraldi mini-nimekiri: foto, mõõt, tähtaeg ja tarneaadress — hooajal segunevad detailid kergesti. See võtab minuti, aga säästab tunde.</p><p>Kui te nummerdate tellimused või annate neile selged nimed (nt “Isa A”, “Vanaisa B”), väheneb risk, et tarne märkused lähevad segi.</p>\n<p>Lisaks vaadake hooajalist juhendit: <a href='/et/blog/joulukingitus-2026'>Jõulukingitus 2026</a>.</p><p>Lisaks vaadake hooajalist juhendit: <a href='/et/blog/joulukingitus-naisele'>Jõulukingitus naisele</a>.</p><p>Lisaks vaadake hooajalist juhendit: <a href='/et/blog/joulukingitus-mehele'>Jõulukingitus mehele</a>.</p><p>Üldised kingi- ja portreejuhised leiate ka <a href='/et/blog/personaalne-kingitus'>personaalne kingitus</a> ning <a href='/et/blog/kunstiline-portree'>kunstiline portree</a> artiklitest (Dream Arti nimega eraldi artiklit meie blogis hetkel pole — need juhendid katavad sarnase kavatsuse).</p><p>Kui te mõtlete mõõtu ja seina, lugege <a href='/et/blog/seinapilt-tellimine'>seinapilt tellimine</a> ja <a href='/et/blog/pilt-louendil'>pilt lõuendil</a> juhendeid.</p>\n<h2>CTA: telli täna, et tähtaeg jääks kontrolli alla</h2><p>Hooaja kingid kannatavad viivitust halvasti. Alustage <a href='https://www.popart.ee'>PopArt.ee</a> tellimusest, märkige tähtaeg ja kinnitage eelvaade enne trükki — nii jäävad nii king kui ka närvid kontrolli alla.</p>",
  "faqs": [
    {
      "question": "Millal tellida isadepäeva kingitus?",
      "answer": "Planeerige varakult enne isadepäeva; nagu iga isiklik tellimus, sõltub kõik eelvaate ja järjekorra vahel. Tarne üle Eesti on levinud; täpne päev sõltub piirkonnast ja kullerist."
    },
    {
      "question": "Kas isadepäeva kingitus jõuab õigeks ajaks, kui tellin hilja?",
      "answer": "Märgige tellimuses tähtaeg ja küsige ausalt, mis on jõutav — parem on aus plaan kui pettumus."
    },
    {
      "question": "Kas portree sobib isale, kes ei taha “lärmakat” kingi?",
      "answer": "Jah, kui valite rahuliku stiili ja klassikalise kompositsiooni; eelvaade aitab kinnitada tooni."
    },
    {
      "question": "Mis foto sobib kõige paremini?",
      "answer": "Ühine hetk lastega või austusväärne portree — väldi liiga teatraalset poosi, kui isa stiil on reserveeritud."
    },
    {
      "question": "Kas tarne üle Eesti on võimalik?",
      "answer": "Jah. Tarne üle Eesti on levinud; täpne päev sõltub piirkonnast ja kullerist."
    },
    {
      "question": "Kuidas valida mõõtu?",
      "answer": "Mõõtke sein või valige universaalsem mõõt; mockup telefonis aitab kiiresti."
    },
    {
      "question": "Mis teeb kingi premium?",
      "answer": "Trüki viimistlus ja turvaline protsess — need on isale sageli arusaadavad “kvaliteedi märgid”."
    }
  ],
  "relatedSlugs": [
    "joulukingitus-2026",
    "joulukingitus-naisele",
    "joulukingitus-mehele",
    "personaalne-kingitus"
  ],
  "internalLinks": [
    {
      "href": "/et/blog/joulukingitus-2026",
      "label": "Jõulukingitus 2026"
    },
    {
      "href": "/et/blog/joulukingitus-naisele",
      "label": "Jõulukingitus naisele"
    },
    {
      "href": "/et/blog/joulukingitus-mehele",
      "label": "Jõulukingitus mehele"
    },
    {
      "href": "/et/blog/kunstiline-portree",
      "label": "Kunstiline portree juhend"
    },
    {
      "href": "https://www.popart.ee",
      "label": "PopArt.ee tellimus"
    }
  ]
}
